setup.py
JS_Prob.egg-info/PKG-INFO
JS_Prob.egg-info/SOURCES.txt
JS_Prob.egg-info/dependency_links.txt
JS_Prob.egg-info/not-zip-safe
JS_Prob.egg-info/top_level.txt
JS_distributions/Binomialdistribution.py
JS_distributions/Gaussiandistribution.py
JS_distributions/Generaldistribution.py
JS_distributions/__init__.py